README.rst
setup.py
authn/__init__.py
pyauthn.egg-info/PKG-INFO
pyauthn.egg-info/SOURCES.txt
pyauthn.egg-info/dependency_links.txt
pyauthn.egg-info/requires.txt
pyauthn.egg-info/top_level.txt